{"is_source_file": true, "format": "JavaScript (React JSX)", "description": "This file defines a React functional component called TrendsPreview, which renders a list of trend items with their titles, summaries, and optional tags. It handles loading and error states and displays appropriate messages or content accordingly.", "external_files": ["react"], "external_methods": [], "published": ["default export (TrendsPreview component)"], "classes": [], "methods": [{"name": "TrendsPreview({ trends, loading, error })", "description": "React functional component that displays a list of AI trends with handling for loading and error states.", "scope": "", "scopeKind": ""}], "calls": ["React", "Array.isArray", "String"], "search-terms": ["TrendsPreview", "trend items", "trend grid", "loading trends", "error message", "trend tags", "React component"], "state": 2, "file_id": 14, "knowledge_revision": 29, "git_revision": "", "ctags": [{"_type": "tag", "name": "TrendsPreview", "path": "/home/kavia/workspace/code-generation/ai-trends-report-generator-for-mechanical-engineering-188692-188701/frontend_react/src/components/TrendsPreview.js", "pattern": "/^export default function TrendsPreview({ trends, loading, error }) {$/", "language": "JavaScript", "kind": "function", "signature": "({ trends, loading, error })"}], "hash": "a43675d256bced1a85ef96971109790a", "format-version": 4, "code-base-name": "frontend_react", "filename": "frontend_react/src/components/TrendsPreview.js", "revision_history": [{"29": ""}]}